{
    "# American Indian and Alaska Native Population": {
        "CT187200": 39.0,
        "CT195720": 16.0,
        "CT197200": 32.0,
        "CT197300": 50.0,
        "CT197410": 27.0,
        "CT197420": 54.0,
        "CT197500": 63.0,
        "CT197600": 17.0,
        "CT197700": 58.0,
        "CT980010": 0.0
    },
    "# Asian Population": {
        "CT187200": 418.0,
        "CT195720": 187.0,
        "CT197200": 1599.0,
        "CT197300": 741.0,
        "CT197410": 406.0,
        "CT197420": 467.0,
        "CT197500": 566.0,
        "CT197600": 536.0,
        "CT197700": 2984.0,
        "CT980010": 94.0
    },
    "# Black Population": {
        "CT187200": 39.0,
        "CT195720": 34.0,
        "CT197200": 40.0,
        "CT197300": 61.0,
        "CT197410": 83.0,
        "CT197420": 76.0,
        "CT197500": 75.0,
        "CT197600": 60.0,
        "CT197700": 115.0,
        "CT980010": 1.0
    },
    "# Hispanic Population": {
        "CT187200": 2454.0,
        "CT195720": 1713.0,
        "CT197200": 2104.0,
        "CT197300": 1782.0,
        "CT197410": 1439.0,
        "CT197420": 2168.0,
        "CT197500": 2312.0,
        "CT197600": 1341.0,
        "CT197700": 1579.0,
        "CT980010": 24.0
    },
    "# Households w/ Income $100 000 to $124 999": {
        "CT187200": 48.0,
        "CT195720": 75.0,
        "CT197200": 117.0,
        "CT197300": 137.0,
        "CT197410": 141.0,
        "CT197420": 150.0,
        "CT197500": 106.0,
        "CT197600": 34.0,
        "CT197700": 97.0,
        "CT980010": 11.0
    },
    "# Households w/ Income $125 000 to $149 999": {
        "CT187200": 39.0,
        "CT195720": 52.0,
        "CT197200": 59.0,
        "CT197300": 91.0,
        "CT197410": 105.0,
        "CT197420": 65.0,
        "CT197500": 44.0,
        "CT197600": 20.0,
        "CT197700": 33.0,
        "CT980010": 3.0
    },
    "# Households w/ Income $15 000 to $24 999": {
        "CT187200": 94.0,
        "CT195720": 71.0,
        "CT197200": 98.0,
        "CT197300": 177.0,
        "CT197410": 179.0,
        "CT197420": 155.0,
        "CT197500": 176.0,
        "CT197600": 35.0,
        "CT197700": 304.0,
        "CT980010": 15.0
    },
    "# Households w/ Income $150 000 to $199 999": {
        "CT187200": 73.0,
        "CT195720": 13.0,
        "CT197200": 16.0,
        "CT197300": 62.0,
        "CT197410": 55.0,
        "CT197420": 53.0,
        "CT197500": 58.0,
        "CT197600": 30.0,
        "CT197700": 15.0,
        "CT980010": 0.0
    },
    "# Households w/ Income $200 000 and Over": {
        "CT187200": 8.0,
        "CT195720": 4.0,
        "CT197200": 0.0,
        "CT197300": 59.0,
        "CT197410": 154.0,
        "CT197420": 62.0,
        "CT197500": 143.0,
        "CT197600": 31.0,
        "CT197700": 8.0,
        "CT980010": 0.0
    },
    "# Households w/ Income $25 000 to $34 999": {
        "CT187200": 87.0,
        "CT195720": 86.0,
        "CT197200": 119.0,
        "CT197300": 175.0,
        "CT197410": 131.0,
        "CT197420": 141.0,
        "CT197500": 206.0,
        "CT197600": 79.0,
        "CT197700": 192.0,
        "CT980010": 3.0
    },
    "# Households w/ Income $35 000 to $49 999": {
        "CT187200": 155.0,
        "CT195720": 129.0,
        "CT197200": 184.0,
        "CT197300": 218.0,
        "CT197410": 176.0,
        "CT197420": 141.0,
        "CT197500": 220.0,
        "CT197600": 270.0,
        "CT197700": 285.0,
        "CT980010": 0.0
    },
    "# Households w/ Income $50 000 to $74 999": {
        "CT187200": 164.0,
        "CT195720": 95.0,
        "CT197200": 230.0,
        "CT197300": 325.0,
        "CT197410": 243.0,
        "CT197420": 182.0,
        "CT197500": 239.0,
        "CT197600": 186.0,
        "CT197700": 277.0,
        "CT980010": 6.0
    },
    "# Households w/ Income $75 000 to $99 999": {
        "CT187200": 78.0,
        "CT195720": 121.0,
        "CT197200": 117.0,
        "CT197300": 250.0,
        "CT197410": 227.0,
        "CT197420": 180.0,
        "CT197500": 153.0,
        "CT197600": 62.0,
        "CT197700": 189.0,
        "CT980010": 2.0
    },
    "# Households w/ Income Less than $15 000": {
        "CT187200": 125.0,
        "CT195720": 203.0,
        "CT197200": 177.0,
        "CT197300": 183.0,
        "CT197410": 202.0,
        "CT197420": 171.0,
        "CT197500": 188.0,
        "CT197600": 150.0,
        "CT197700": 444.0,
        "CT980010": 19.0
    },
    "# Households w/ Rent $1 000-$1 249": {
        "CT187200": 161.0,
        "CT195720": 65.0,
        "CT197200": 112.0,
        "CT197300": 169.0,
        "CT197410": 122.0,
        "CT197420": 95.0,
        "CT197500": 259.0,
        "CT197600": 143.0,
        "CT197700": 199.0,
        "CT980010": 18.0
    },
    "# Households w/ Rent $1 250-$1 499": {
        "CT187200": 9.0,
        "CT195720": 196.0,
        "CT197200": 52.0,
        "CT197300": 211.0,
        "CT197410": 176.0,
        "CT197420": 56.0,
        "CT197500": 122.0,
        "CT197600": 90.0,
        "CT197700": 221.0,
        "CT980010": 9.0
    },
    "# Households w/ Rent $1 500-$1 999": {
        "CT187200": 68.0,
        "CT195720": 26.0,
        "CT197200": 9.0,
        "CT197300": 177.0,
        "CT197410": 151.0,
        "CT197420": 206.0,
        "CT197500": 351.0,
        "CT197600": 76.0,
        "CT197700": 139.0,
        "CT980010": 0.0
    },
    "# Households w/ Rent $2 000+": {
        "CT187200": 16.0,
        "CT195720": 31.0,
        "CT197200": 0.0,
        "CT197300": 124.0,
        "CT197410": 122.0,
        "CT197420": 106.0,
        "CT197500": 49.0,
        "CT197600": 21.0,
        "CT197700": 6.0,
        "CT980010": 0.0
    },
    "# Households w/ Rent $250-$499": {
        "CT187200": 34.0,
        "CT195720": 64.0,
        "CT197200": 74.0,
        "CT197300": 73.0,
        "CT197410": 21.0,
        "CT197420": 43.0,
        "CT197500": 59.0,
        "CT197600": 10.0,
        "CT197700": 101.0,
        "CT980010": 0.0
    },
    "# Households w/ Rent $500-$749": {
        "CT187200": 106.0,
        "CT195720": 126.0,
        "CT197200": 31.0,
        "CT197300": 213.0,
        "CT197410": 91.0,
        "CT197420": 160.0,
        "CT197500": 226.0,
        "CT197600": 164.0,
        "CT197700": 457.0,
        "CT980010": 4.0
    },
    "# Households w/ Rent $750-$999": {
        "CT187200": 90.0,
        "CT195720": 203.0,
        "CT197200": 190.0,
        "CT197300": 240.0,
        "CT197410": 115.0,
        "CT197420": 255.0,
        "CT197500": 153.0,
        "CT197600": 212.0,
        "CT197700": 379.0,
        "CT980010": 0.0
    },
    "# Households w/ Rent less than $250": {
        "CT187200": 0.0,
        "CT195720": 0.0,
        "CT197200": 15.0,
        "CT197300": 9.0,
        "CT197410": 0.0,
        "CT197420": 8.0,
        "CT197500": 17.0,
        "CT197600": 12.0,
        "CT197700": 9.0,
        "CT980010": 9.0
    },
    "# Housing  Occupied Units": {
        "CT187200": 871.0,
        "CT195720": 849.0,
        "CT197200": 1117.0,
        "CT197300": 1677.0,
        "CT197410": 1613.0,
        "CT197420": 1300.0,
        "CT197500": 1533.0,
        "CT197600": 897.0,
        "CT197700": 1844.0,
        "CT980010": 59.0
    },
    "# Housing  Owner Occupied": {
        "CT187200": 387.0,
        "CT195720": 138.0,
        "CT197200": 568.0,
        "CT197300": 401.0,
        "CT197410": 788.0,
        "CT197420": 371.0,
        "CT197500": 269.0,
        "CT197600": 169.0,
        "CT197700": 314.0,
        "CT980010": 19.0
    },
    "# Housing  Renter Occupied": {
        "CT187200": 484.0,
        "CT195720": 711.0,
        "CT197200": 549.0,
        "CT197300": 1276.0,
        "CT197410": 825.0,
        "CT197420": 929.0,
        "CT197500": 1264.0,
        "CT197600": 728.0,
        "CT197700": 1530.0,
        "CT980010": 40.0
    },
    "# Housing  Units": {
        "CT187200": 937.0,
        "CT195720": 915.0,
        "CT197200": 1181.0,
        "CT197300": 1817.0,
        "CT197410": 1762.0,
        "CT197420": 1415.0,
        "CT197500": 1710.0,
        "CT197600": 996.0,
        "CT197700": 2001.0,
        "CT980010": 61.0
    },
    "# Other Race Population": {
        "CT187200": 1067.0,
        "CT195720": 796.0,
        "CT197200": 891.0,
        "CT197300": 601.0,
        "CT197410": 564.0,
        "CT197420": 706.0,
        "CT197500": 876.0,
        "CT197600": 543.0,
        "CT197700": 653.0,
        "CT980010": 5.0
    },
    "# Population (Pop)": {
        "CT187200": 3187.0,
        "CT195720": 2376.0,
        "CT197200": 3810.0,
        "CT197300": 3953.0,
        "CT197410": 3766.0,
        "CT197420": 3534.0,
        "CT197500": 3988.0,
        "CT197600": 2455.0,
        "CT197700": 5249.0,
        "CT980010": 167.0
    },
    "# Vacant Units": {
        "CT187200": 66.0,
        "CT195720": 66.0,
        "CT197200": 64.0,
        "CT197300": 140.0,
        "CT197410": 149.0,
        "CT197420": 115.0,
        "CT197500": 177.0,
        "CT197600": 99.0,
        "CT197700": 157.0,
        "CT980010": 2.0
    },
    "# White Non-Hispanic Population": {
        "CT187200": 264.0,
        "CT195720": 376.0,
        "CT197200": 117.0,
        "CT197300": 1170.0,
        "CT197410": 1555.0,
        "CT197420": 748.0,
        "CT197500": 892.0,
        "CT197600": 454.0,
        "CT197700": 457.0,
        "CT980010": 47.0
    },
    "Housing  Median Rent ($)": {
        "CT187200": 1019.0,
        "CT195720": 953.0,
        "CT197200": 910.0,
        "CT197300": 1108.0,
        "CT197410": 1321.0,
        "CT197420": 998.0,
        "CT197500": 1157.0,
        "CT197600": 960.0,
        "CT197700": 874.0,
        "CT980010": 1097.0
    }
}